Workbook

Sheet Summary
A1: Football Club - Season Summary
A2: Every number on this page is calculated from the other 4 tabs. Blue = typed-in input, black = formula, green = taken from another tab.
A4: Measure | B4: Value | C4: What it means
A5: Inputs
A6: Season months | B6: 10 | C6: From Team_Info (SQL). Typed-in input.
A7: League matches | B7: =Matches!D22 -> 14 | C7: Counted on the Matches tab.
A8: Paid people | B8: 5 | C8: People with a salary above zero (SQL view vw_payroll). Typed-in input.
A9: Key numbers
A10: Total revenue (EUR) | B10: =Revenue!$B$10 -> 42000 | C10: All money coming in.
A11: Total expenses (EUR) | B11: =Expenses!$B$22 -> 35833 | C11: All money going out.
A12: Net result (EUR) | B12: =B10-B11 -> 6167 | C12: Revenue minus expenses. Positive = surplus, negative = loss.
A13: Net margin | B13: =B12/B10 -> 0.14683333 | C13: Net result as a share of revenue.
A14: Revenue / expenses ratio | B14: =B10/B11 -> 1.1721039 | C14: Above 1.00 means revenue covers expenses.
A15: Expenses per month (EUR) | B15: =B11/B6 -> 3583.3 | C15: Average monthly spending.
A16: Expenses per league match (EUR) | B16: =B11/B7 -> 2559.5 | C16: Full season spending divided by number of matches.
A17: Reserve in months of expenses | B17: =B12/B15 -> 1.7210393 | C17: How many months of spending the surplus could pay.
A18: Share of the 2 largest revenue sources | B18: =Revenue!B12 -> 0.95238095 | C18: Close to 100% = the club depends on very few sources.
A19: Share of the 3 largest expense categories | B19: =Expenses!B24 -> 0.81419362 | C19: Shows how concentrated the spending is.
A20: Average home match cost (EUR) | B20: =Matches!B24 -> 140 | C20: Match cost of one home match.
A21: Average away match cost (EUR) | B21: =Matches!C24 -> 96.857143 | C21: Match cost of one away match, including travel fuel.
A22: Expenses per paid person (EUR) | B22: =B11/B8 -> 7166.6 | C22: Total spending divided by people on payroll.
A23: Main findings (text updates with the numbers)
A24: ="1. The season ends with a "&IF(B12>=0,"surplus","loss")&" of "&TEXT(ABS(B12),"#,##0")&" EUR ("&TEXT(B13,"0.0%")&" of revenue)." -> 1. The season ends with a surplus of 6,167 EUR (14.7% of revenue).
A25: ="2. The 2 largest revenue sources give "&TEXT(B18,"0.0%")&" of all revenue, so the club depends on very few sources." -> 2. The 2 largest revenue sources give 95.2% of all revenue, so the club depends on very few sources.
A26: ="3. The 3 largest expense categories make "&TEXT(B19,"0.0%")&" of all spending." -> 3. The 3 largest expense categories make 81.4% of all spending.
A27: ="4. Revenue can fall by about "&TEXT(MAX(0,B12/B10),"0.0%")&" before the season ends in a loss." -> 4. Revenue can fall by about 14.7% before the season ends in a loss.
A28: ="5. A home match costs "&TEXT(B20,"#,##0")&" EUR on average and an away match "&TEXT(B21,"#,##0.0")&" EUR." -> 5. A home match costs 140 EUR on average and an away match 96.9 EUR.
A30: Control: do these tabs match the SQL database?
A31: Check | B31: This workbook | C31: SQL value / status
A32: Total revenue (EUR) | B32: =B10 -> 42000 | C32: 42000
A33: Total expenses (EUR) | B33: =B11 -> 35833 | C33: 35833
A34: Total match-day cost (EUR) | B34: =Matches!E19 -> 1658 | C34: 1658
A35: Overall status | B35: =IF(AND(B32=C32,B33=C33,B34=C34),"ALL OK","CHECK") -> ALL OK | C35: SQL values are typed in (blue) from vw_kpi_summary and vw_match_day_costs.

Sheet Revenue
A1: Revenue by source
A2: Question: where does the money come from? Blue values come from SQL view vw_revenue_by_source.
A4: Revenue Source | B4: Amount (EUR) | C4: Share of Total | D4: Cumulative Share
A5: Fundraising Dinners | B5: 20000 | C5: =B5/$B$10 -> 0.47619048 | D5: =SUM($C$5:C5) -> 0.47619048
A6: Village Funding | B6: 20000 | C6: =B6/$B$10 -> 0.47619048 | D6: =SUM($C$5:C6) -> 0.95238095
A7: Sponsorships | B7: 2000 | C7: =B7/$B$10 -> 0.047619048 | D7: =SUM($C$5:C7) -> 1
A8: Other Revenue | B8: 0 | C8: =B8/$B$10 -> 0 | D8: =SUM($C$5:C8) -> 1
A9: Ticket Sales | B9: 0 | C9: =B9/$B$10 -> 0 | D9: =SUM($C$5:C9) -> 1
A10: Total | B10: =SUM(B5:B9) -> 42000 | C10: =SUM(C5:C9) -> 1
A12: Share of the 2 largest sources | B12: =D6 -> 0.95238095
A13: Number of active sources (amount > 0) | B13: =COUNTIF(B5:B9,">0") -> 3
A15: How to read it: sources are sorted from largest to smallest. If 2 sources give almost all revenue, losing one of them is a serious risk.

Sheet Expenses
A1: Expenses by category
A2: Question: where does the money go? Blue values come from SQL view vw_expenses_by_category.
A4: Expense Category | B4: Cost (EUR) | C4: Share of Total | D4: Cumulative Share
A5: Coaching Staff | B5: 13000 | C5: =B5/$B$22 -> 0.36279407 | D5: =SUM($C$5:C5) -> 0.36279407
A6: Player Salaries | B6: 12000 | C6: =B6/$B$22 -> 0.33488684 | D6: =SUM($C$5:C6) -> 0.69768091
A7: Equipment & Medical Supplies | B7: 4175 | C7: =B7/$B$22 -> 0.11651271 | D7: =SUM($C$5:C7) -> 0.81419362
A8: Electricity | B8: 2500 | C8: =B8/$B$22 -> 0.069768091 | D8: =SUM($C$5:C8) -> 0.88396171
A9: Accountant | B9: 1000 | C9: =B9/$B$22 -> 0.027907236 | D9: =SUM($C$5:C9) -> 0.91186895
A10: Water | B10: 1000 | C10: =B10/$B$22 -> 0.027907236 | D10: =SUM($C$5:C10) -> 0.93977618
A11: Referees | B11: 840 | C11: =B11/$B$22 -> 0.023442079 | D11: =SUM($C$5:C11) -> 0.96321826
A12: Travel | B12: 678 | C12: =B12/$B$22 -> 0.018921106 | D12: =SUM($C$5:C12) -> 0.98213937
A13: Lawyer | B13: 500 | C13: =B13/$B$22 -> 0.013953618 | D13: =SUM($C$5:C13) -> 0.99609299
A14: Match Doctor | B14: 140 | C14: =B14/$B$22 -> 0.0039070131 | D14: =SUM($C$5:C14) -> 1
A15: Insurance | B15: 0 | C15: =B15/$B$22 -> 0 | D15: =SUM($C$5:C15) -> 1
A16: Other Operating Expenses | B16: 0 | C16: =B16/$B$22 -> 0 | D16: =SUM($C$5:C16) -> 1
... A21: Website, Social Media, Advertising & Printing | B21: 0 | C21: =B21/$B$22 -> 0 | D21: =SUM($C$5:C21) -> 1
A22: Total | B22: =SUM(B5:B21) -> 35833 | C22: =SUM(C5:C21) -> 1
A24: Share of the 3 largest categories | B24: =D7 -> 0.81419362
A25: Categories needed to reach 80% of spending | B25: =COUNTIF(D5:D21,"<0.8")+1 -> 3
A26: Categories with zero cost | B26: =COUNTIF(B5:B21,0) -> 7
A28: How to read it: categories are sorted from largest to smallest. A few categories usually explain most of the spending (the 80/20 idea).

Sheet Matches
A1: Cost per league match
A2: Question: what does one match cost, at home and away? Blue values come from SQL view vw_match_day_costs.
A4: Match | B4: Home / Away | C4: Match Cost (EUR) | D4: Travel Fuel (EUR) | E4: Total Cost (EUR)
A5: H01 | B5: Home | C5: 140 | D5: 0 | E5: =C5+D5 -> 140
A6: H02 | B6: Home | C6: 140 | D6: 0 | E6: =C6+D6 -> 140
A7: H03 | B7: Home | C7: 140 | D7: 0 | E7: =C7+D7 -> 140
A8: H04 | B8: Home | C8: 140 | D8: 0 | E8: =C8+D8 -> 140
A9: H05 | B9: Home | C9: 140 | D9: 0 | E9: =C9+D9 -> 140
A10: H06 | B10: Home | C10: 140 | D10: 0 | E10: =C10+D10 -> 140
A11: H07 | B11: Home | C11: 140 | D11: 0 | E11: =C11+D11 -> 140
A12: A01 | B12: Away | C12: 0 | D12: 12 | E12: =C12+D12 -> 12
A13: A02 | B13: Away | C13: 0 | D13: 60 | E13: =C13+D13 -> 60
A14: A03 | B14: Away | C14: 0 | D14: 96 | E14: =C14+D14 -> 96
A15: A04 | B15: Away | C15: 0 | D15: 108 | E15: =C15+D15 -> 108
A16: A05 | B16: Away | C16: 0 | D16: 114 | E16: =C16+D16 -> 114
... A18: A07 | B18: Away | C18: 0 | D18: 156 | E18: =C18+D18 -> 156
A19: Total | C19: =SUM(C5:C18) -> 980 | D19: =SUM(D5:D18) -> 678 | E19: =SUM(E5:E18) -> 1658
A21: Measure | B21: Home | C21: Away | D21: All
A22: Number of matches | B22: =COUNTIF($B$5:$B$18,"Home") -> 7 | C22: =COUNTIF($B$5:$B$18,"Away") -> 7 | D22: =B22+C22 -> 14
A23: Total cost (EUR) | B23: =SUMIFS($E$5:$E$18,$B$5:$B$18,"Home") -> 980 | C23: =SUMIFS($E$5:$E$18,$B$5:$B$18,"Away") -> 678 | D23: =B23+C23 -> 1658
A24: Average cost per match (EUR) | B24: =B23/B22 -> 140 | C24: =C23/C22 -> 96.857143 | D24: =D23/D22 -> 118.42857
A25: Cheapest match (EUR) | B25: =_xlfn.MINIFS($E$5:$E$18,$B$5:$B$18,"Home") -> 140 | C25: =_xlfn.MINIFS($E$5:$E$18,$B$5:$B$18,"Away") -> 12 | D25: =MIN(B25:C25) -> 12
A26: Most expensive match (EUR) | B26: =_xlfn.MAXIFS($E$5:$E$18,$B$5:$B$18,"Home") -> 140 | C26: =_xlfn.MAXIFS($E$5:$E$18,$B$5:$B$18,"Away") -> 156 | D26: =MAX(B26:C26) -> 156
A28: How to read it: total cost = match cost (referees, doctor, other) + travel fuel. Only away matches have travel fuel.

Sheet What_If
A1: What if...?
A2: Question: how safe is the season if things go worse than planned? Yellow cells are assumptions you can change.
A4: Revenue falls by | B4: -0.1 | C4: Assumption: change the yellow cell
A5: Expenses rise by | B5: 0.1 | C5: Assumption: change the yellow cell
A6: Season months | B6: =Summary!B6 -> 10
A8: Scenario | B8: Revenue (EUR) | C8: Expenses (EUR) | D8: Net Result (EUR) | E8: Net Margin | F8: Reserve (months of expenses)
A9: Base case (as planned) | B9: =Revenue!$B$10 -> 42000 | C9: =Expenses!$B$22 -> 35833 | D9: =B9-C9 -> 6167 | E9: =IF(B9=0,0,D9/B9) -> 0.14683333 | F9: =IF(C9=0,0,D9/(C9/$B$6)) -> 1.7210393
A10: Lose the largest revenue source | B10: =Revenue!$B$10-MAX(Revenue!$B$5:$B$9) -> 22000 | C10: =Expenses!$B$22 -> 35833 | D10: =B10-C10 -> -13833 | E10: =IF(B10=0,0,D10/B10) -> -0.62877273 | F10: =IF(C10=0,0,D10/(C10/$B$6)) -> -3.860408
A11: Revenue falls by the % in B4 | B11: =Revenue!$B$10*(1+$B$4) -> 37800 | C11: =Expenses!$B$22 -> 35833 | D11: =B11-C11 -> 1967 | E11: =IF(B11=0,0,D11/B11) -> 0.052037037 | F11: =IF(C11=0,0,D11/(C11/$B$6)) -> 0.54893534
A12: Expenses rise by the % in B5 | B12: =Revenue!$B$10 -> 42000 | C12: =Expenses!$B$22*(1+$B$5) -> 39416.3 | D12: =B12-C12 -> 2583.7 | E12: =IF(B12=0,0,D12/B12) -> 0.061516667 | F12: =IF(C12=0,0,D12/(C12/$B$6)) -> 0.65549024
A13: Both changes together | B13: =Revenue!$B$10*(1+$B$4) -> 37800 | C13: =Expenses!$B$22*(1+$B$5) -> 39416.3 | D13: =B13-C13 -> -1616.3 | E13: =IF(B13=0,0,D13/B13) -> -0.042759259 | F13: =IF(C13=0,0,D13/(C13/$B$6)) -> -0.41005878
A15: How to read it: a negative Net Result means a loss. Reserve = how many months of expenses the surplus would pay for.
